labugr/__config__.py
labugr/__init__.py
labugr/setup.py
labugr/audio/__init__.py
labugr/audio/decoder.py
labugr/audio/setup.py
labugr/audio/wavfile.py
labugr/audio/audioread/__init__.py
labugr/audio/audioread/ffdec.py
labugr/audio/audioread/gstdec.py
labugr/audio/audioread/macca.py
labugr/audio/audioread/maddec.py
labugr/audio/audioread/rawread.py
labugr/audio/audioread/setup.py
labugr/audio/audioread/version.py
labugr/audio/tests/test_wavfile.py
labugr/audio/tests/data/chicken.mp3
labugr/audio/tests/data/example_1.nc
labugr/audio/tests/data/test-44100Hz-2ch-32bit-float-be.wav
labugr/audio/tests/data/test-44100Hz-2ch-32bit-float-le.wav
labugr/audio/tests/data/test-44100Hz-le-1ch-4bytes-early-eof.wav
labugr/audio/tests/data/test-44100Hz-le-1ch-4bytes-incomplete-chunk.wav
labugr/audio/tests/data/test-44100Hz-le-1ch-4bytes.wav
labugr/audio/tests/data/test-48000Hz-2ch-64bit-float-le-wavex.wav
labugr/audio/tests/data/test-8000Hz-le-2ch-1byteu.wav
labugr/dependencies/__init__.py
labugr/dependencies/cycler.py
labugr/dependencies/six.py
labugr/doc/__init__.py
labugr/doc/ayuda.py
labugr/doc/documentacion.py
labugr/doc/traducir.py
labugr/doc/doc-ESP/StateSpace-es.txt
labugr/doc/doc-ESP/StateSpace.txt
labugr/doc/doc-ESP/TransferFunction-es.txt
labugr/doc/doc-ESP/TransferFunction.txt
labugr/doc/doc-ESP/ZerosPolesGain-es.txt
labugr/doc/doc-ESP/ZerosPolesGain.txt
labugr/doc/doc-ESP/all-es.txt
labugr/doc/doc-ESP/all.txt
labugr/doc/doc-ESP/allclose-es.txt
labugr/doc/doc-ESP/allclose.txt
labugr/doc/doc-ESP/any-es.txt
labugr/doc/doc-ESP/any.txt
labugr/doc/doc-ESP/arange-es.txt
labugr/doc/doc-ESP/arange.txt
labugr/doc/doc-ESP/arccos-es.txt
labugr/doc/doc-ESP/arccos.txt
labugr/doc/doc-ESP/arccosh-es.txt
labugr/doc/doc-ESP/arccosh.txt
labugr/doc/doc-ESP/arcsin-es.txt
labugr/doc/doc-ESP/arcsin.txt
labugr/doc/doc-ESP/arcsinh-es.txt
labugr/doc/doc-ESP/arcsinh.txt
labugr/doc/doc-ESP/arctan-es.txt
labugr/doc/doc-ESP/arctan.txt
labugr-1.1.dist-info/DESCRIPTION.rst
labugr-1.1.dist-info/METADATA
labugr-1.1.dist-info/RECORD
labugr-1.1.dist-info/WHEEL
labugr-1.1.dist-info/metadata.json
labugr-1.1.dist-info/top_level.txt
