Metadata-Version: 2.0
Name: labugr
Version: 1.1
Summary: Laboratorio de señales UGR
Home-page: http://github.com/lserraga/labUGR
Author: Luis Serra Garcia
Author-email: lsgarcia@correo.ugr.es
License: MIT
Keywords: signal analysis
Platform: Windows
Platform: Linux
Platform: MacOS
Requires-Python: >=3.4.*
Requires-Dist: numpy (>=1.8.2)
Requires-Dist: mpmath
Requires-Dist: matplotlib
Requires-Dist: pyaudio
Provides-Extra: dev
Requires-Dist: cython; extra == 'dev'
Provides-Extra: test
Requires-Dist: pytest; extra == 'test'
Requires-Dist: nose; extra == 'test'
